phemexboy/__init__.py
phemexboy/exceptions.py
phemexboy/proxy.py
phemexboy/api/__init__.py
phemexboy/api/public.py
phemexboy/api/auth/__init__.py
phemexboy/api/auth/client.py
phemexboy/api/auth/order.py
phemexboy/api/auth/position.py
phemexboy/helpers/__init__.py
phemexboy/helpers/conversions.py
phemexboy/interfaces/__init__.py
phemexboy/interfaces/public_interface.py
phemexboy/interfaces/auth/__init__.py
phemexboy/interfaces/auth/client_interface.py
phemexboy/interfaces/auth/order_interface.py
phemexboy/interfaces/auth/position_interface.py
phemexboy/tests/__init__.py
phemexboy/tests/auth_tests.py
phemexboy/tests/client_tests.py
phemexboy/tests/future_tests.py
phemexboy/tests/proxy_tests.py
phemexboy/tests/public_tests.py
phemexboy/tests/spot_tests.py
phemexboy-2.0.0.dist-info/LICENSE
phemexboy-2.0.0.dist-info/WHEEL
phemexboy-2.0.0.dist-info/METADATA
phemexboy-2.0.0.dist-info/RECORD
