Metadata-Version: 2.1
Name: phemexboy
Version: 2.0.0
Summary: Phemex API Wrapper in Python
Author-email: Marques Traylor <traylorboy@proton.me>
Classifier: License :: OSI Approved :: MIT License
Requires-Dist: ccxt
Requires-Dist: botboy
Requires-Dist: python-dotenv
Project-URL: Home, https://github.com/TraylorBoy/PhemexBoy
